evolution_openai/__init__.py
evolution_openai/client.py
evolution_openai/exceptions.py
evolution_openai/py.typed
evolution_openai/token_manager.py
evolution_openai-1.0.4.dist-info/METADATA
evolution_openai-1.0.4.dist-info/WHEEL
evolution_openai-1.0.4.dist-info/licenses/LICENSE
evolution_openai-1.0.4.dist-info/RECORD
