Metadata-Version: 2.3
Name: evolution-openai
Version: 1.0.4
Summary: Evolution OpenAI with automatic token management
Project-URL: Homepage, https://github.com/cloud-ru-tech/evolution-openai-python
Project-URL: Repository, https://github.com/cloud-ru-tech/evolution-openai-python.git
Project-URL: Documentation, https://cloud-ru-tech.github.io/evolution-openai-python/
Project-URL: Bug Reports, https://github.com/cloud-ru-tech/evolution-openai-python/issues
Project-URL: Changelog, https://github.com/cloud-ru-tech/evolution-openai-python/blob/main/CHANGELOG.md
Author-email: Evolution ML Inference Team <support@cloud.ru>
Maintainer-email: Evolution ML Inference Team <support@cloud.ru>
Keywords: ai,api,chatgpt,client,cloud.ru,gpt,ml,openai,sdk
Classifier: Intended Audience :: Developers
Classifier: License :: OSI Approved :: MIT License
Classifier: Operating System :: MacOS
Classifier: Operating System :: Microsoft :: Windows
Classifier: Operating System :: OS Independent
Classifier: Operating System :: POSIX
Classifier: Operating System :: POSIX :: Linux
Classifier: Programming Language :: Python :: 3
Classifier: Programming Language :: Python :: 3.8
Classifier: Programming Language :: Python :: 3.9
Classifier: Programming Language :: Python :: 3.10
Classifier: Programming Language :: Python :: 3.11
Classifier: Programming Language :: Python :: 3.12
Classifier: Topic :: Internet :: WWW/HTTP :: HTTP Servers
Classifier: Topic :: Scientific/Engineering :: Artificial Intelligence
Classifier: Topic :: Software Development :: Libraries :: Python Modules
Classifier: Typing :: Typed
Requires-Python: >=3.8
Requires-Dist: httpx<1,>=0.23.0
Requires-Dist: openai<2,>=1.30.0
Requires-Dist: python-dotenv<2,>=1.0.0
Requires-Dist: requests<3,>=2.25.0
